CHANGES.rst
LICENSE.txt
MANIFEST.in
README.rst
setup.py
src/pheather/__init__.py
src/pheather.egg-info/PKG-INFO
src/pheather.egg-info/SOURCES.txt
src/pheather.egg-info/dependency_links.txt
src/pheather.egg-info/entry_points.txt
src/pheather.egg-info/not-zip-safe
src/pheather.egg-info/requires.txt
src/pheather.egg-info/top_level.txt