Metadata-Version: 1.0
Name: pheather
Version: 0.1.1
Summary: Store Pandas data frame as ZODB blobs
Home-page: https://github.com/jimfulton/pheather
Author: Jim Fulton
Author-email: jim@jimfulton.info
License: MIT
Keywords: persistent,pandas,data frame,zodb,persistent,database
Platform: UNKNOWN
